{"cameraMode":{"drawMode":0,"name":"Shaded","section":"Shading Mode"},"sceneLighting":false,"audioPlay":false,"sceneViewState":{"m_AlwaysRefresh":false,"showFog":true,"showSkybox":false,"showFlares":true,"showImageEffects":true,"showParticleSystems":true,"showVisualEffectGraphs":true,"m_FxEnabled":true},"in2DMode":false,"pivot":{"x":7.450580596923828e-9,"y":0.2140466868877411,"z":0.0},"rotation":{"x":0.10530996322631836,"y":0.582451581954956,"z":-0.0764441266655922,"w":0.8023840188980103},"size":0.3448244035243988,"orthographic":false}